{ //pages数组中第一项表示应用启动页，参考：https://uniapp.dcloud.io/collocation/pages
	"pages": [
		{
			"path": "pages/index/index",
			"style": {
				"navigationBarTitleText": "Campus Transaction",
				"backgroundColor":"#FAFAFA"
			}
		},
		{
			"path": "pages/login/login",
			"style": {}
		},
		{
			"path": "pages/login/forget",
			"style": {}
		}, {
			"path": "pages/login/register",
			"style": {}
		},
		{
			"path": "pages/search/search", // 搜索和筛选页
			"style": {
				"enablePullDownRefresh": false
			}
		}, {
			"path": "pages/appraise/appraise",
			"style": {}
		}, {
			"path": "pages/detail/reservation", // 预约详情
			"style": {
				"enablePullDownRefresh":true
			}
		}, {
			"path": "pages/detail/commodity", // 物品详情
			"style": {
				"enablePullDownRefresh": true
			}
		}, {
			"path": "pages/detail/notice", //通告详情
			"style": {
				"enablePullDownRefresh":true
			}
		}, {
			"path": "pages/reservations/reservations", // 预约列表
			"style": {}
		}, {
			"path": "pages/account/account",
			"style": {
				"backgroundColor": "#CCCCCC",
				"enablePullDownRefresh":true
			}
		}
	],
	"globalStyle": {
		"navigationStyle": "custom",
		"animationType":"zoom-out"
	},
	"sitemapLocation": "sitemap.json"
}
